<?xml version="1.0" encoding="UTF-8" standalone="yes"?>
<ns2:purchaseNoticeEP xsi:schemaLocation="http://zakupki.gov.ru/223/integration/schema/TFF-5.2 http://zakupki.gov.ru/223/integration/schema/TFF-5.2/purchase.xsd" xmlns="http://zakupki.gov.ru/223fz/types/1" xmlns:ns10="http://zakupki.gov.ru/223fz/purchasePlan/1" xmlns:ns11="http://zakupki.gov.ru/223fz/purchasePlanProject/1" xmlns:ns12="http://zakupki.gov.ru/223fz/purchasePlanProjectAdditionalPosition/1" xmlns:ns13="http://zakupki.gov.ru/223fz/contract/1" xmlns:ns14="http://zakupki.gov.ru/223fz/missedNotice/1" xmlns:ns15="http://zakupki.gov.ru/223fz/reference/1" xmlns:ns16="http://zakupki.gov.ru/223fz/stopCommodity/1" xmlns:ns17="http://zakupki.gov.ru/223fz/decisionSuspension/1" xmlns:ns18="http://zakupki.gov.ru/223fz/purchasePlanAdditionalPosition/1" xmlns:ns19="http://zakupki.gov.ru/223fz/webRequest/1" xmlns:ns2="http://zakupki.gov.ru/223fz/purchase/1" xmlns:xsi="http://www.w3.org/2001/XMLSchema-instance" xmlns:ns3="http://zakupki.gov.ru/223fz/dishonestSupplier/1" xmlns:ns4="http://zakupki.gov.ru/223fz/machineryListInfo/1" xmlns:ns5="http://zakupki.gov.ru/223fz/revenue/1" xmlns:ns6="http://zakupki.gov.ru/223fz/orderClauseList/1" xmlns:ns7="http://zakupki.gov.ru/223fz/disagreementProtocol/1" xmlns:ns8="http://zakupki.gov.ru/223fz/complaint/1" xmlns:ns9="http://zakupki.gov.ru/223fz/notificationIssue/1">
    <header>
        <guid>4d09d43b-83c3-43bc-9ce7-5ee1d6dc14c3</guid>
        <createDateTime>2017-03-16T11:30:27</createDateTime>
    </header>
    <ns2:body>
        <ns2:item>
            <guid>5434134b-c098-41ff-b0c8-e24f8806d73f</guid>
            <ns2:purchaseNoticeEPData>
                <ns2:guid>5434134b-c098-41ff-b0c8-e24f8806d73f</ns2:guid>
                <ns2:createDateTime>2017-03-16T11:29:01</ns2:createDateTime>
                <ns2:urlOOS>https://zakupki.gov.ru/223/purchase/private/purchase/notice-info/details.html?noticeInfoId=5884138</ns2:urlOOS>
                <ns2:registrationNumber>31704896487</ns2:registrationNumber>
                <ns2:name>Поставка сувенирной продукции для нужд ФГБОУ ВО "РЭУ им. Г.В. Плеханова"</ns2:name>
                <ns2:customer>
                    <mainInfo>
                        <fullName>ФЕДЕРАЛЬНОЕ ГОСУДАРСТВЕННОЕ БЮДЖЕТНОЕ ОБРАЗОВАТЕЛЬНОЕ УЧРЕЖДЕНИЕ ВЫСШЕГО ОБРАЗОВАНИЯ "РОССИЙСКИЙ ЭКОНОМИЧЕСКИЙ УНИВЕРСИТЕТ ИМЕНИ Г.В. ПЛЕХАНОВА"</fullName>
                        <shortName>ФГБОУ ВО "РЭУ ИМ. Г.В. ПЛЕХАНОВА", РЭУ ИМ. Г.В. ПЛЕХАНОВА</shortName>
                        <iko>87705043493770501001</iko>
                        <inn>7705043493</inn>
                        <kpp>770501001</kpp>
                        <ogrn>1037700012008</ogrn>
                        <legalAddress>117997, Г МОСКВА, ПЕР СТРЕМЯННЫЙ, дом ДОМ 36</legalAddress>
                        <postalAddress>117997, город Москва, Стремянный переулок, дом 36</postalAddress>
                        <phone>7-499-2374114</phone>
                        <email>eis@rea.ru</email>
                        <okato>45286560000</okato>
                        <okpo>02068686</okpo>
                    </mainInfo>
                </ns2:customer>
                <ns2:purchaseMethodCode>3363</ns2:purchaseMethodCode>
                <ns2:purchaseCodeName>Закупка у единственного поставщика (исполнителя, подрядчика)</ns2:purchaseCodeName>
                <ns2:placer>
                    <mainInfo>
                        <fullName>ФЕДЕРАЛЬНОЕ ГОСУДАРСТВЕННОЕ БЮДЖЕТНОЕ ОБРАЗОВАТЕЛЬНОЕ УЧРЕЖДЕНИЕ ВЫСШЕГО ОБРАЗОВАНИЯ "РОССИЙСКИЙ ЭКОНОМИЧЕСКИЙ УНИВЕРСИТЕТ ИМЕНИ Г.В. ПЛЕХАНОВА"</fullName>
                        <shortName>ФГБОУ ВО "РЭУ ИМ. Г.В. ПЛЕХАНОВА", РЭУ ИМ. Г.В. ПЛЕХАНОВА</shortName>
                        <iko>87705043493770501001</iko>
                        <inn>7705043493</inn>
                        <kpp>770501001</kpp>
                        <ogrn>1037700012008</ogrn>
                        <legalAddress>117997, Г МОСКВА, ПЕР СТРЕМЯННЫЙ, дом ДОМ 36</legalAddress>
                        <postalAddress>117997, город Москва, Стремянный переулок, дом 36</postalAddress>
                        <phone>7-499-2374114</phone>
                        <email>eis@rea.ru</email>
                        <okato>45286560000</okato>
                        <okpo>02068686</okpo>
                    </mainInfo>
                </ns2:placer>
                <ns2:contact>
                    <phone>+7 (495) 9581746</phone>
                    <email>monitoring@rea.ru</email>
                    <organization>
                        <mainInfo>
                            <fullName>ФЕДЕРАЛЬНОЕ ГОСУДАРСТВЕННОЕ БЮДЖЕТНОЕ ОБРАЗОВАТЕЛЬНОЕ УЧРЕЖДЕНИЕ ВЫСШЕГО ОБРАЗОВАНИЯ "РОССИЙСКИЙ ЭКОНОМИЧЕСКИЙ УНИВЕРСИТЕТ ИМЕНИ Г.В. ПЛЕХАНОВА"</fullName>
                            <shortName>ФГБОУ ВО "РЭУ ИМ. Г.В. ПЛЕХАНОВА", РЭУ ИМ. Г.В. ПЛЕХАНОВА</shortName>
                            <iko>87705043493770501001</iko>
                            <inn>7705043493</inn>
                            <kpp>770501001</kpp>
                            <ogrn>1037700012008</ogrn>
                            <legalAddress>117997, Г МОСКВА, ПЕР СТРЕМЯННЫЙ, дом ДОМ 36</legalAddress>
                            <postalAddress>117997, город Москва, Стремянный переулок, дом 36</postalAddress>
                            <phone>7-499-2374114</phone>
                            <email>eis@rea.ru</email>
                            <okato>45286560000</okato>
                            <okpo>02068686</okpo>
                        </mainInfo>
                    </organization>
                </ns2:contact>
                <ns2:publicationDateTime>2017-03-16T11:30:27</ns2:publicationDateTime>
                <ns2:documentationDelivery/>
                <ns2:status>P</ns2:status>
                <ns2:version>1</ns2:version>
                <ns2:notDishonest>false</ns2:notDishonest>
                <ns2:attachments>
                    <totalDocumentsCount>3</totalDocumentsCount>
                    <document>
                        <guid>1d79760c-6e83-4d38-a8d6-ef50f21430f8</guid>
                        <createDateTime>2017-03-16T11:30:08</createDateTime>
                        <fileName>Спецификация.xlsx</fileName>
                        <description>Спецификация</description>
                        <url>http://zakupki.gov.ru/223/purchase/public/download/download.html?id=30100113</url>
                    </document>
                    <document>
                        <guid>285b1255-3aa4-4ccd-8eee-59695b8153c9</guid>
                        <createDateTime>2017-03-16T11:29:59</createDateTime>
                        <fileName>Договор.doc</fileName>
                        <description>Договор</description>
                        <url>http://zakupki.gov.ru/223/purchase/public/download/download.html?id=30100099</url>
                    </document>
                    <document>
                        <guid>7514221e-09de-4a47-af9a-5cd531723547</guid>
                        <createDateTime>2017-03-16T11:30:04</createDateTime>
                        <fileName>Извещение и Документация.doc</fileName>
                        <description>Извещение и Документация</description>
                        <url>http://zakupki.gov.ru/223/purchase/public/download/download.html?id=30100105</url>
                    </document>
                </ns2:attachments>
                <ns2:modificationDate>2017-03-16T11:30:27</ns2:modificationDate>
                <ns2:saveUserId>115746</ns2:saveUserId>
                <ns2:deliveryPlaceIndication>DIFFERENT_PLACE</ns2:deliveryPlaceIndication>
                <ns2:emergency>false</ns2:emergency>
                <ns2:jointPurchase>false</ns2:jointPurchase>
                <ns2:lots>
                    <lot>
                        <guid>7b1c9025-2b5c-40d5-9ec8-53de4a565ca9</guid>
                        <ordinalNumber>1</ordinalNumber>
                        <lotEditEnabled>false</lotEditEnabled>
                        <lotData>
                            <subject>Поставка сувенирной продукции для нужд ФГБОУ ВО "РЭУ им. Г.В. Плеханова"</subject>
                            <currency>
                                <code>RUB</code>
                                <digitalCode>643</digitalCode>
                                <name>Российский рубль</name>
                            </currency>
                            <initialSum>390800.00</initialSum>
                            <deliveryPlace>
                                <state>Центральный федеральный округ</state>
                                <region>Москва</region>
                                <regionOkato>45000000000</regionOkato>
                                <address>г. Москва, Стремянный пер., дом 36</address>
                            </deliveryPlace>
                            <lotItems>
                                <newCodes>true</newCodes>
                                <lotItem>
                                    <guid>8464f137-48c4-4dd0-a44c-76fb6c8f182b</guid>
                                    <ordinalNumber>1</ordinalNumber>
                                    <okpd2>
                                        <code>32.99.21.110</code>
                                        <name>Зонты от дождя и солнца</name>
                                    </okpd2>
                                    <okved2>
                                        <code>46.4</code>
                                        <name>Торговля оптовая непродовольственными потребительскими товарами</name>
                                    </okved2>
                                    <okei>
                                        <code>796</code>
                                        <name>Штука</name>
                                    </okei>
                                    <qty>15</qty>
                                    <additionalInfo>Зонтик-трость (Размер: в сложенном виде длина 93 см, Цвет: белый с синим, Ручка: металл. Упакован в фирменный футляр РЭУ с логотипом Университета, нанесенного методом горячего прессования из фольги серебряного цвета. Производство: Италия</additionalInfo>
                                </lotItem>
                                <lotItem>
                                    <guid>5719ada1-10fb-49b6-b5fb-4a05a7df16ff</guid>
                                    <ordinalNumber>2</ordinalNumber>
                                    <okpd2>
                                        <code>14.19.23.120</code>
                                        <name>Шали, шарфы, вуали, кроме трикотажных или вязаных</name>
                                    </okpd2>
                                    <okved2>
                                        <code>46.4</code>
                                        <name>Торговля оптовая непродовольственными потребительскими товарами</name>
                                    </okved2>
                                    <okei>
                                        <code>796</code>
                                        <name>Штука</name>
                                    </okei>
                                    <qty>32</qty>
                                    <additionalInfo>Шарф мужской. Состав: 90 % модал, 10 % кашемир, Цвет: Коричневый, Черный, Размер: 70 × 170 см., Материал: Модал - модернизированное вискозное волокно, получаемое из натуральных древесных стволов. Мягкая шелковистая ткань из сочетания модала и кашемира хорошо впитывает влагу, красиво драпируется, мало электризуется и обладает высокими теплозащитными свойствами. Край изделия: По продольной стороне - подшитый край, по поперечной - бахрома. Край изделия: По продольной стороне - подшитый край, по поперечной - бахрома. Упакован в фирменный футляр РЭУ с логотипом Университета, нанесенного методом горячего прессования из фольги серебряного цвета. Производитель: Италия</additionalInfo>
                                </lotItem>
                                <lotItem>
                                    <guid>e35173f3-9f6b-4a5b-9329-517b193409da</guid>
                                    <ordinalNumber>3</ordinalNumber>
                                    <okpd2>
                                        <code>15.12.19.110</code>
                                        <name>Изделия прочие из кожи натуральной или композиционной, не включенные в другие группировки</name>
                                    </okpd2>
                                    <okved2>
                                        <code>46.4</code>
                                        <name>Торговля оптовая непродовольственными потребительскими товарами</name>
                                    </okved2>
                                    <okei>
                                        <code>796</code>
                                        <name>Штука</name>
                                    </okei>
                                    <qty>27</qty>
                                    <additionalInfo>Ремень кожаный мужской 3.5х120 см., Ремень выполнен из натуральной плетеной кожи, пряжка металлическая, цвет золото и обтянутая черной кожей. Упакован в фирменный футляр РЭУ с логотипом Университета, нанесенного методом горячего прессования из фольги серебряного цвета. Производство: Италия</additionalInfo>
                                </lotItem>
                                <lotItem>
                                    <guid>ae551fd9-6ce1-49f0-9369-a6060395b2d3</guid>
                                    <ordinalNumber>4</ordinalNumber>
                                    <okpd2>
                                        <code>15.12.19.110</code>
                                        <name>Изделия прочие из кожи натуральной или композиционной, не включенные в другие группировки</name>
                                    </okpd2>
                                    <okved2>
                                        <code>46.4</code>
                                        <name>Торговля оптовая непродовольственными потребительскими товарами</name>
                                    </okved2>
                                    <okei>
                                        <code>796</code>
                                        <name>Штука</name>
                                    </okei>
                                    <qty>20</qty>
                                    <additionalInfo>Мужской кошелек-клатч на молнии, Кошелек-клатч закрывается на молнии. На задней стенке ручка. 3 отделения для купюр. 2 скрытых отделения. 6 отделений для пластиковых или кредитных карт.  2 отделения для фото или пропуска. Фурнитура – металл. Упакован в фирменный футляр РЭУ с логотипом Университета, нанесенного методом горячего прессования из фольги серебряного цвета. Производство: Италия</additionalInfo>
                                </lotItem>
                                <lotItem>
                                    <guid>d13ad52e-6635-487a-8d36-21b86699a1bb</guid>
                                    <ordinalNumber>5</ordinalNumber>
                                    <okpd2>
                                        <code>15.12.19.110</code>
                                        <name>Изделия прочие из кожи натуральной или композиционной, не включенные в другие группировки</name>
                                    </okpd2>
                                    <okved2>
                                        <code>46.4</code>
                                        <name>Торговля оптовая непродовольственными потребительскими товарами</name>
                                    </okved2>
                                    <okei>
                                        <code>796</code>
                                        <name>Штука</name>
                                    </okei>
                                    <qty>20</qty>
                                    <additionalInfo>Мужской кожаный кошелек на 2-х молниях. Состав: натуральная кожа. У кошелька 2 основных отделения. В первом отделении: 4 отделения для купюр и 1 отделение на молнии. Во 2 отделении: 14 отделений для пластиковых или кредитных карт, 2 скрытых кармана, отделение для фото или пропуска, большая, съемная, монетница на молнии.  Фурнитура – металл. Упакован в фирменный футляр РЭУ с логотипом Университета, нанесенного методом горячего прессования из фольги серебряного цвета. Производство: Италия</additionalInfo>
                                </lotItem>
                            </lotItems>
                            <forSmallOrMiddle>true</forSmallOrMiddle>
                            <excludePurchaseFromPlan>false</excludePurchaseFromPlan>
                            <subcontractorsRequirement>false</subcontractorsRequirement>
                            <ignoredPurchase>false</ignoredPurchase>
                            <centralized>false</centralized>
                        </lotData>
                        <deliveryPlaceIndication>GL</deliveryPlaceIndication>
                        <jointLotData>
                            <jointLot>false</jointLot>
                        </jointLotData>
                        <lotPlanInfo>
                            <planRegistrationNumber>2160209814</planRegistrationNumber>
                            <planGuid>c4bd5cba-87c0-49f7-bb30-fc71957281c4</planGuid>
                            <positionNumber>671</positionNumber>
                            <lotPlanPosition>COMMODITY</lotPlanPosition>
                            <positionGuid>13664ef2-d7a7-44ba-9adc-353a9fdd6422</positionGuid>
                        </lotPlanInfo>
                        <cancelled>false</cancelled>
                    </lot>
                </ns2:lots>
            </ns2:purchaseNoticeEPData>
        </ns2:item>
    </ns2:body>
</ns2:purchaseNoticeEP>
