<?xml version="1.0" encoding="UTF-8" standalone="yes"?>
<ns2:contract xsi:schemaLocation="http://zakupki.gov.ru/223/integration/schema/TFF-5.0 http://zakupki.gov.ru/223/integration/schema/TFF-5.0/Types.xsd" xmlns="http://zakupki.gov.ru/223fz/types/1" xmlns:ns10="http://zakupki.gov.ru/223fz/complaint/1" xmlns:ns11="http://zakupki.gov.ru/223fz/decisionSuspension/1" xmlns:ns12="http://zakupki.gov.ru/223fz/purchasePlanAdditionalPosition/1" xmlns:ns13="http://zakupki.gov.ru/223fz/notificationIssue/1" xmlns:ns14="http://zakupki.gov.ru/223fz/purchasePlanProject/1" xmlns:ns15="http://zakupki.gov.ru/223fz/purchasePlanProjectAdditionalPosition/1" xmlns:ns16="http://zakupki.gov.ru/223fz/disagreementProtocol/1" xmlns:ns17="http://zakupki.gov.ru/223fz/reference/1" xmlns:ns18="http://zakupki.gov.ru/223fz/stopCommodity/1" xmlns:ns19="http://zakupki.gov.ru/223fz/webRequest/1" xmlns:ns2="http://zakupki.gov.ru/223fz/contract/1" xmlns:xsi="http://www.w3.org/2001/XMLSchema-instance" xmlns:ns3="http://zakupki.gov.ru/223fz/dishonestSupplier/1" xmlns:ns4="http://zakupki.gov.ru/223fz/purchase/1" xmlns:ns5="http://zakupki.gov.ru/223fz/machineryListInfo/1" xmlns:ns6="http://zakupki.gov.ru/223fz/revenue/1" xmlns:ns7="http://zakupki.gov.ru/223fz/orderClauseList/1" xmlns:ns8="http://zakupki.gov.ru/223fz/purchasePlan/1" xmlns:ns9="http://zakupki.gov.ru/223fz/missedNotice/1">
    <header>
        <guid>031c863a-8190-48bd-87cc-f0c1534eacb9</guid>
        <createDateTime>2016-05-25T15:40:37</createDateTime>
    </header>
    <ns2:body>
        <ns2:item>
            <guid>4e5a25a7-c475-4da0-b5c9-34d52626a74b</guid>
            <ns2:contractData>
                <ns2:guid>292d19bf-946e-474c-9960-9618a631262b</ns2:guid>
                <ns2:registrationNumber>57707083893160020510001</ns2:registrationNumber>
                <ns2:notice44>false</ns2:notice44>
                <ns2:termination>false</ns2:termination>
                <ns2:extension>false</ns2:extension>
                <ns2:prolongation>false</ns2:prolongation>
                <ns2:lotNum>1</ns2:lotNum>
                <ns2:urlOOS>https://zakupki.gov.ru/223/contract/private/contract/view/general-information.html?id=1683489&amp;viewMode=VSRI</ns2:urlOOS>
                <ns2:createDateTime>2016-05-25T15:31:13</ns2:createDateTime>
                <ns2:customer>
                    <mainInfo>
                        <fullName>ПУБЛИЧНОЕ АКЦИОНЕРНОЕ ОБЩЕСТВО "СБЕРБАНК РОССИИ"</fullName>
                        <shortName>ПАО СБЕРБАНК</shortName>
                        <iko>57707083893775001001</iko>
                        <inn>7707083893</inn>
                        <kpp>775001001</kpp>
                        <ogrn>1027700132195</ogrn>
                        <legalAddress>117997, г МОСКВА, ул ВАВИЛОВА, дом 19</legalAddress>
                        <postalAddress>117997, г. Москва, ул. Вавилова, 19</postalAddress>
                        <phone>7-495-7473789</phone>
                        <fax>7-495-7473667</fax>
                        <email>Gref_p@sberbank.ru</email>
                        <okato>45293554000</okato>
                        <okopf>48</okopf>
                        <okopfName>Хозяйственные товарищества и общества</okopfName>
                        <okpo>00032537</okpo>
                        <customerRegistrationDate>2007-06-13T00:00:00</customerRegistrationDate>
                    </mainInfo>
                </ns2:customer>
                <ns2:placer>
                    <mainInfo>
                        <fullName>ПУБЛИЧНОЕ АКЦИОНЕРНОЕ ОБЩЕСТВО "СБЕРБАНК РОССИИ"</fullName>
                        <shortName>ПАО СБЕРБАНК</shortName>
                        <iko>57707083893775001001</iko>
                        <inn>7707083893</inn>
                        <kpp>775001001</kpp>
                        <ogrn>1027700132195</ogrn>
                        <legalAddress>117997, г МОСКВА, ул ВАВИЛОВА, дом 19</legalAddress>
                        <postalAddress>117997, г. Москва, ул. Вавилова, 19</postalAddress>
                        <phone>7-495-7473789</phone>
                        <fax>7-495-7473667</fax>
                        <email>Gref_p@sberbank.ru</email>
                        <okato>45293554000</okato>
                        <okpo>00032537</okpo>
                    </mainInfo>
                </ns2:placer>
                <ns2:publicationDate>2016-05-25T15:40:37</ns2:publicationDate>
                <ns2:status>P</ns2:status>
                <ns2:version>1</ns2:version>
                <ns2:digitalPurchase>true</ns2:digitalPurchase>
                <ns2:digitalPurchaseCode>400001</ns2:digitalPurchaseCode>
                <ns2:provider>false</ns2:provider>
                <ns2:changeContract>false</ns2:changeContract>
                <ns2:attachments>
                    <totalDocumentsCount>1</totalDocumentsCount>
                    <document>
                        <guid>8b202252-e63a-477f-a32a-65b9bb8ba94c</guid>
                        <createDateTime>2016-05-25T12:32:04</createDateTime>
                        <fileName>Договор У (2).pdf</fileName>
                        <description>Сканкопия договора</description>
                        <url>https://zakupki.gov.ru/223/contract/private/download/download.html?id=3517344</url>
                        <registrationNumber>57707083893160020510002</registrationNumber>
                    </document>
                </ns2:attachments>
                <ns2:contractRegNumber>57707083893160020510000</ns2:contractRegNumber>
                <ns2:name>19/16-54</ns2:name>
                <ns2:contractDate>2016-05-20</ns2:contractDate>
                <ns2:purchaseNoticeInfo>
                    <ns2:guid>5e6bcc7b-a687-4a90-bd0b-13e4d8ce07ca</ns2:guid>
                    <ns2:purchaseNoticeNumber>31603619795</ns2:purchaseNoticeNumber>
                    <ns2:publicationDateTime>2016-04-29T14:57:24</ns2:publicationDateTime>
                    <ns2:name>[33185] Выбор организации на выполнение работ по текущему ремонту  объектов Белгородского отделения №8592 ПАО Сбербанк: Д/О №8592/0513расположенного по адресу: Белгородская обл, г. Грайворон,ул. Ленина, д.14а ; Д/О №8592/018 расположенного по адресу: г. Белгород, б-р Юности, д.10;  Д/О №8592/047 расположенного по адресу: г. Белгород, Народный б-р, д.87/89;  Д/О №8592/002 расположенного по адресу: г. Белгород, ул. Преображенская, д.69;  Д/О №8592/014 расположенного по адресу г.Белгород, пр-т Б.Хмельницкого, д.160, среди поставщиков, аккредитованных по итогам квалификационного отбора (Протокол №24 от 02.06.2015г., Протокол №32 от 24.07.2015г., Протокол №41 от 08.09.2015г. Протокол №53 от 05.11.2015г., Протокол №3 от 25.01.2016г., Протокол №15 от 30.03.2016г., Протокол №21 от 28.04.2016г.).</ns2:name>
                </ns2:purchaseNoticeInfo>
                <ns2:lotGuid>6a4cc365-9df4-4fab-b0fe-236f9bdfa223</ns2:lotGuid>
                <ns2:subjectContract>[33185] Выбор организации на выполнение работ по текущему ремонту  объектов Белгородского отделения №8592 ПАО Сбербанк: Д/О №8592/0513расположенного по адресу: Белгородская обл, г. Грайворон,ул. Ленин</ns2:subjectContract>
                <ns2:purchaseTypeInfo>
                    <ns2:code>40000</ns2:code>
                    <ns2:name>Иной способ закупки, предусмотренный правовым актом заказчика, указанным в части 1 статьи 2 Федерального закона</ns2:name>
                </ns2:purchaseTypeInfo>
                <ns2:supplierInfo>
                    <ns2:name>ООО «УОР-2»</ns2:name>
                    <ns2:inn>3123087938</ns2:inn>
                    <ns2:kpp>312301001</ns2:kpp>
                    <ns2:okpo>59390551</ns2:okpo>
                    <ns2:type>L</ns2:type>
                    <ns2:provider>true</ns2:provider>
                    <ns2:providerCode>30</ns2:providerCode>
                    <ns2:subcontractor>false</ns2:subcontractor>
                    <ns2:nonResident>false</ns2:nonResident>
                    <ns2:registrationDate>2002-12-31</ns2:registrationDate>
                    <ns2:tax>true</ns2:tax>
                    <ns2:okopf>12165</ns2:okopf>
                    <ns2:okopfName>Общества с ограниченной ответственностью</ns2:okopfName>
                    <ns2:address>
                        <ns2:country>
                            <name>РОССИЯ</name>
                            <digitalCode>643</digitalCode>
                        </ns2:country>
                        <ns2:postCode>308000</ns2:postCode>
                        <ns2:oktmo>14701000</ns2:oktmo>
                        <ns2:region>
                            <ns2:fullName>Белгородская область</ns2:fullName>
                        </ns2:region>
                    </ns2:address>
                </ns2:supplierInfo>
                <ns2:hasSubcontractor>false</ns2:hasSubcontractor>
                <ns2:price>725000</ns2:price>
                <ns2:rubPrice>725000</ns2:rubPrice>
                <ns2:currency>
                    <code>RUB</code>
                    <digitalCode>643</digitalCode>
                    <name>Российский рубль</name>
                </ns2:currency>
                <ns2:startExecutionDate>2016-05-20</ns2:startExecutionDate>
                <ns2:endExecutionDate>2018-06-30</ns2:endExecutionDate>
                <ns2:contractPositions>
                    <ns2:contractPosition>
                        <ns2:guid>dfce12e0-50e1-449e-9dca-5b939c71200a</ns2:guid>
                        <ns2:name>Выполнение работ по текущему ремонту  объектов Белгородского отделения №8592 ПАО Сбербанк: Д/О №8592/0513расположенного по адресу: Белгородская обл, г. Грайворон,ул. Ленина, д.14а ; Д/О №8592/018 расположенного по адресу: г. Белгород, б-р Юности, д.10;  Д/О №8592/047 расположенного по адресу: г. Белгород, Народный б-р, д.87/89;  Д/О №8592/002 расположенного по адресу: г. Белгород, ул. Преображенская, д.69;  Д/О №8592/014 расположенного по адресу г.Белгород, пр-т Б.Хмельницкого, д.160 (387 м2)</ns2:name>
                        <ns2:ordinalNumber>1</ns2:ordinalNumber>
                        <ns2:okpd2>
                            <code>41.20.40.000</code>
                            <name>Работы строительные по возведению нежилых зданий и сооружений (работы по строительству новых объектов, возведению пристроек, реконструкции и ремонту зданий)</name>
                        </ns2:okpd2>
                        <ns2:impossibleToDetermineAttr>false</ns2:impossibleToDetermineAttr>
                        <ns2:okei>
                            <code>055</code>
                            <name>Квадратный метр</name>
                        </ns2:okei>
                        <ns2:qty>387</ns2:qty>
                    </ns2:contractPosition>
                </ns2:contractPositions>
                <ns2:contractConfirmingDocs>
                    <ns2:contractDoc>
                        <ns2:confirmingDocCode>1</ns2:confirmingDocCode>
                        <ns2:confirmingDocCodeTitle>Протокол, составленный по результатам закупки</ns2:confirmingDocCodeTitle>
                        <ns2:protocolInfoGuid>c1959376-8128-4fcc-94c4-dbf8246720ca</ns2:protocolInfoGuid>
                        <ns2:protocolName>СБ: протокол подведения итогов/выбор победителя 31603619795-01</ns2:protocolName>
                        <ns2:docDate>2016-05-20</ns2:docDate>
                        <ns2:docNum>31603619795-01</ns2:docNum>
                    </ns2:contractDoc>
                </ns2:contractConfirmingDocs>
                <ns2:hasOkpdAndOkdpRows>false</ns2:hasOkpdAndOkdpRows>
                <ns2:hasOkpd2Rows>true</ns2:hasOkpd2Rows>
            </ns2:contractData>
        </ns2:item>
    </ns2:body>
</ns2:contract>
